type_parse/__init__.py
type_parse/base.py
type_parse/py.typed
type_parse/utils.py
type_parse-0.1.1.dist-info/WHEEL
type_parse-0.1.1.dist-info/METADATA
type_parse-0.1.1.dist-info/LICENSE
type_parse-0.1.1.dist-info/RECORD
