Metadata-Version: 2.1
Name: type-parse
Version: 0.1.1
Summary: Parse the markup language with Python type hints.
License: MIT
Author: nahco314
Author-email: nahco3_ta@yahoo.co.jp
Requires-Python: >=3.8.1,<4.0.0
Classifier: License :: OSI Approved :: MIT License
Classifier: Programming Language :: Python :: 3
Classifier: Programming Language :: Python :: 3.9
Classifier: Programming Language :: Python :: 3.10
Classifier: Programming Language :: Python :: 3.11
